README.md
setup.py
pibble/__init__.py
pibble/__main__.py
pibble/setup.py
pibble.egg-info/PKG-INFO
pibble.egg-info/SOURCES.txt
pibble.egg-info/dependency_links.txt
pibble.egg-info/entry_points.txt
pibble.egg-info/requires.txt
pibble.egg-info/top_level.txt
pibble/api/__init__.py
pibble/api/base.py
pibble/api/configuration.py
pibble/api/exceptions.py
pibble/api/client/__init__.py
pibble/api/client/base.py
pibble/api/client/googlerpc.py
pibble/api/client/wrapper.py
pibble/api/client/apachethrift/__init__.py
pibble/api/client/apachethrift/wrapper.py
pibble/api/client/file/__init__.py
pibble/api/client/file/base.py
pibble/api/client/file/ftp.py
pibble/api/client/file/hdfs.py
pibble/api/client/file/local.py
pibble/api/client/file/sftp.py
pibble/api/client/webservice/__init__.py
pibble/api/client/webservice/apachethrift.py
pibble/api/client/webservice/base.py
pibble/api/client/webservice/jsonapi.py
pibble/api/client/webservice/soap.py
pibble/api/client/webservice/wrapper.py
pibble/api/client/webservice/rpc/__init__.py
pibble/api/client/webservice/rpc/base.py
pibble/api/client/webservice/rpc/jsonrpc.py
pibble/api/client/webservice/rpc/xmlrpc.py
pibble/api/helpers/__init__.py
pibble/api/helpers/apachethrift.py
pibble/api/helpers/authentication.py
pibble/api/helpers/googlerpc.py
pibble/api/helpers/store.py
pibble/api/helpers/wrappers.py
pibble/api/meta/__init__.py
pibble/api/meta/base.py
pibble/api/meta/helpers.py
pibble/api/middleware/__init__.py
pibble/api/middleware/base.py
pibble/api/middleware/screening.py
pibble/api/middleware/apachethrift/__init__.py
pibble/api/middleware/apachethrift/base.py
pibble/api/middleware/apachethrift/screening.py
pibble/api/middleware/database/__init__.py
pibble/api/middleware/database/orm.py
pibble/api/middleware/file/__init__.py
pibble/api/middleware/file/temp.py
pibble/api/middleware/googlerpc/__init__.py
pibble/api/middleware/googlerpc/authentication.py
pibble/api/middleware/googlerpc/base.py
pibble/api/middleware/googlerpc/metadata.py
pibble/api/middleware/webservice/__init__.py
pibble/api/middleware/webservice/base.py
pibble/api/middleware/webservice/limit.py
pibble/api/middleware/webservice/origin.py
