Metadata-Version: 2.1
Name: pibble
Version: 0.5.9
Summary: A framework for developing webapps quickly and easily using Python
Author: Benjamin Paine
Author-email: painebenjamin@gmail.com
License: gpl-3.0
Provides-Extra: mysql
Provides-Extra: postgresql
Provides-Extra: mssql
Provides-Extra: thrift
Provides-Extra: grpc
Provides-Extra: browser
Provides-Extra: imaging
Provides-Extra: cherrypy
Provides-Extra: gunicorn
Provides-Extra: werkzeug
Provides-Extra: build
Provides-Extra: all
